{
  "date_published": "2013-09-26",
  "canonical_url": "https://riskandinsurance.com/oklahoma-workers-comp-lawsuit-defies-logic/",
  "brand": "rih",
  "content_type": "article",
  "source_url": "https://riskandinsurance.com/oklahoma-workers-comp-lawsuit-defies-logic/",
  "publisher": "Risk & Insurance",
  "_scraped_at": "2026-05-10T14:35:10.533002+00:00",
  "category": "Claims & The Law",
  "categories": [
    "Claims & The Law"
  ],
  "_missing_fields": [
    "title",
    "body"
  ],
  "_content_hash": ""
}